[{"timestamp":"2025-12-19T00:56:40.160Z","count":0,"uniques":0},{"timestamp":"2025-12-20T01:26:48.105Z","count":0,"uniques":0},{"timestamp":"2025-12-21T00:01:51.610Z","count":0,"uniques":0},{"timestamp":"2025-12-22T02:07:26.415Z","count":0,"uniques":0},{"timestamp":"2025-12-23T01:49:21.596Z","count":0,"uniques":0},{"timestamp":"2025-12-24T01:53:51.547Z","count":0,"uniques":0},{"timestamp":"2025-12-25T00:01:28.676Z","count":0,"uniques":0},{"timestamp":"2025-12-26T01:17:07.859Z","count":0,"uniques":0}]
