[{"timestamp":"2024-02-21T00:52:27.272Z","count":0,"uniques":0},{"timestamp":"2024-02-22T00:01:14.016Z","count":0,"uniques":0},{"timestamp":"2024-02-23T00:01:15.732Z","count":0,"uniques":0},{"timestamp":"2024-02-24T00:33:41.722Z","count":0,"uniques":0},{"timestamp":"2024-02-25T00:41:02.194Z","count":0,"uniques":0},{"timestamp":"2024-02-26T00:01:07.622Z","count":0,"uniques":0},{"timestamp":"2024-02-27T00:00:05.306Z","count":0,"uniques":0},{"timestamp":"2024-02-28T00:35:12.444Z","count":0,"uniques":0}]
