[{"timestamp":"2024-06-03T00:00:34.192Z","count":0,"uniques":0},{"timestamp":"2024-06-04T00:53:56.576Z","count":0,"uniques":0},{"timestamp":"2024-06-05T00:32:01.799Z","count":0,"uniques":0},{"timestamp":"2024-06-06T00:40:07.020Z","count":0,"uniques":0},{"timestamp":"2024-06-07T00:01:00.898Z","count":0,"uniques":0},{"timestamp":"2024-06-08T00:51:52.913Z","count":0,"uniques":0},{"timestamp":"2024-06-09T01:03:39.772Z","count":0,"uniques":0},{"timestamp":"2024-06-10T00:01:29.973Z","count":0,"uniques":0}]
