[{"timestamp":"2026-05-13T00:16:04.864Z","count":0,"uniques":0},{"timestamp":"2026-05-14T01:30:22.286Z","count":0,"uniques":0},{"timestamp":"2026-05-15T01:29:35.695Z","count":0,"uniques":0},{"timestamp":"2026-05-16T00:09:28.062Z","count":0,"uniques":0},{"timestamp":"2026-05-17T01:24:42.466Z","count":0,"uniques":0},{"timestamp":"2026-05-18T01:32:51.856Z","count":0,"uniques":0},{"timestamp":"2026-05-19T01:35:23.432Z","count":0,"uniques":0},{"timestamp":"2026-05-20T01:34:50.956Z","count":0,"uniques":0}]
