[{"timestamp":"2024-12-18T01:08:58.218Z","count":0,"uniques":0},{"timestamp":"2024-12-19T00:00:12.173Z","count":0,"uniques":0},{"timestamp":"2024-12-20T00:57:30.022Z","count":0,"uniques":0},{"timestamp":"2024-12-21T00:34:40.792Z","count":0,"uniques":0},{"timestamp":"2024-12-22T01:36:47.728Z","count":0,"uniques":0},{"timestamp":"2024-12-23T00:41:10.418Z","count":0,"uniques":0},{"timestamp":"2024-12-24T00:37:06.513Z","count":0,"uniques":0},{"timestamp":"2024-12-25T01:13:08.220Z","count":0,"uniques":0}]
